LICENSE
MANIFEST.in
Makefile
README.md
requirements.txt
setup.py
async_pubsub/__init__.py
async_pubsub/base.py
async_pubsub/constants.py
async_pubsub/redis_pubsub.py
async_pubsub/zmq_pubsub.py
async_pubsub.egg-info/PKG-INFO
async_pubsub.egg-info/SOURCES.txt
async_pubsub.egg-info/dependency_links.txt
async_pubsub.egg-info/requires.txt
async_pubsub.egg-info/top_level.txt
tests/__init__.py
tests/test_redis_pubsub.py
tests/test_zmq_pubsub.py